{
  "project_info": {
    "project_number": "107191359996",
    "project_id": "werrahandroid",
    "storage_bucket": "werrahandroid.appspot.com"
  },
  "client": [
    {
      "client_info": {
        "mobilesdk_app_id": "1:107191359996:android:41e0e19473432406ae3a79",
        "android_client_info": {
          "package_name": "com.example.wera"
        }
      },
      "oauth_client": [],
      "api_key": [
        {
          "current_key": "AIzaSyD6uPpyqMNo7W6iwtddTNJlAVdOYEBljFA"
        }
      ],
      "services": {
        "appinvite_service": {
          "other_platform_oauth_client": []
        }
      }
    },
    {
      "client_info": {
        "mobilesdk_app_id": "1:107191359996:android:028ec5f2e8216526ae3a79",
        "android_client_info": {
          "package_name": "com.werrah.wera"
        }
      },
      "oauth_client": [],
      "api_key": [
        {
          "current_key": "AIzaSyD6uPpyqMNo7W6iwtddTNJlAVdOYEBljFA"
        }
      ],
      "services": {
        "appinvite_service": {
          "other_platform_oauth_client": []
        }
      }
    }
  ],
  "configuration_version": "1"
}